argoflow/__init__.py
argoflow/artifacts.py
argoflow/enums.py
argoflow/resources.py
argoflow/task.py
argoflow/workflow.py
argoflow-0.2.0.dist-info/LICENSE
argoflow-0.2.0.dist-info/METADATA
argoflow-0.2.0.dist-info/WHEEL
argoflow-0.2.0.dist-info/top_level.txt
argoflow-0.2.0.dist-info/RECORD
