Metadata-Version: 2.1
Name: argoflow
Version: 0.2.0
Summary: A Python library for building Argo Workflows programmatically
Home-page: https://github.com/D-Ajay-Kumar/argowf-python
Author: D Ajay Kumar
License: UNKNOWN
Project-URL: Bug Tracker, https://github.com/D-Ajay-Kumar/argowf-python/issues
Project-URL: Source Code, https://github.com/D-Ajay-Kumar/argowf-python
Keywords: argo workflows kubernetes devops ci/cd
Platform: UNKNOWN
Requires-Python: >=3.7
License-File: LICENSE
Requires-Dist: requests>=2.0.0
